[
  {
    "id": "nirvana-1993-11-14",
    "artist": "Nirvana",
    "openers": [
      "Breeders",
      "Half Japanese"
    ],
    "date": "1993-11-14",
    "venue": "New York Coliseum",
    "city": "New York, NY",
    "attendees": [
      "Andy",
      "Pete",
      "Chris",
      "Jeremy"
    ],
    "comments": "Oh boy, fill this in later",
    "links": [
      "https://www.setlist.fm/setlist/nirvana/1993/new-york-coliseum-new-york-ny-73d67e89.html",
      "https://www.youtube.com/watch?v=qgpst7b2Tis"
    ],
    "imageUrl": "https://via.placeholder.com/300x200",
    "year": 1993
  },
  {
    "id": "pink-floyd-1994-07-17",
    "artist": "Pink Floyd",
    "openers": [],
    "date": "1994-07-17",
    "venue": "Giants Stadium",
    "city": "East Rutherford, NJ",
    "attendees": [
      "April",
      "Nina",
      "Leo"
    ],
    "comments": "I barely remember the actual show. I do remember 'Shine On You Crazy Diamond'",
    "links": [],
    "imageUrl": "https://via.placeholder.com/300x200",
    "year": 1994
  },
  {
    "id": "smashing-pumpkins-1994-08-05",
    "artist": "Smashing Pumpkins",
    "openers": [],
    "date": "1994-08-05",
    "venue": "Downing Stadium",
    "city": "New York, NY",
    "attendees": [
      "Chris",
      "Pete"
    ],
    "comments": "I may have made this show up. I mean I am pretty sure I saw the Pumpkins twice, and I have a vague memory of going to this, but I'm definitely not sure. This seems too early, but who knows.",
    "links": [
      "https://www.setlist.fm/setlist/the-smashing-pumpkins/1994/downing-stadium-new-york-ny-73d7ced1.html"
    ],
    "imageUrl": "https://via.placeholder.com/300x200",
    "year": 1994
  },
  {
    "id": "nine-inch-nails-1994-12-08",
    "artist": "Nine Inch Nails",
    "openers": [
      "Marilyn Manson"
    ],
    "date": "1994-12-08",
    "venue": "Madison Square Garden",
    "city": "New York, NY",
    "attendees": [
      "Andy",
      "Pete",
      "Chris",
      "Jeff"
    ],
    "comments": "Marilyn Manson was ridiculous, and before him there was a freak show which was fairly disturbing. I remember NIN being pretty awesome. I think there were two drumsets?? Also I crowd surfed in Madison Square Garden down some stairs which in retrospect was pretty crazy.",
    "links": [
      "https://www.setlist.fm/setlist/nine-inch-nails/1994/madison-square-garden-new-york-ny-6bd6d60a.html"
    ],
    "imageUrl": "https://via.placeholder.com/300x200",
    "year": 1994
  },
  {
    "id": "tom-petty-1995-04-11",
    "artist": "Tom Petty",
    "openers": [],
    "date": "1995-04-11",
    "venue": "Richmond Coliseum",
    "city": "Richmond, VA",
    "attendees": [
      "Jill",
      "Jen"
    ],
    "comments": "",
    "links": [
      "https://www.setlist.fm/setlist/tom-petty-and-the-heartbreakers/1995/richmond-coliseum-richmond-va-1bd641c4.html"
    ],
    "imageUrl": "https://via.placeholder.com/300x200",
    "year": 1995
  },
  {
    "id": "beastie-boys-1995-05-23",
    "artist": "Beastie Boys",
    "openers": [],
    "date": "1995-05-23",
    "venue": "Madison Square Garden",
    "city": "New York, NY",
    "attendees": [
      "Pete",
      "Chris",
      "Gerard"
    ],
    "comments": "Barely remember this",
    "links": [
      "https://www.setlist.fm/setlist/beastie-boys/1995/madison-square-garden-new-york-ny-73d67a0d.html"
    ],
    "imageUrl": "https://via.placeholder.com/300x200",
    "year": 1995
  },
  {
    "id": "rem-1995-06-22",
    "artist": "REM",
    "openers": [],
    "date": "1995-06-22",
    "venue": "Madison Square Garden",
    "city": "New York, NY",
    "attendees": [
      "Andy",
      "Pete",
      "Chris",
      "Jeff",
      "Sachin"
    ],
    "comments": "",
    "links": [
      "https://www.setlist.fm/setlist/rem/1995/madison-square-garden-new-york-ny-1bd6b9b0.html"
    ],
    "imageUrl": "https://via.placeholder.com/300x200",
    "year": 1995
  },
  {
    "id": "steve-miller-band-1995-07-31",
    "artist": "Steve Miller Band",
    "openers": [],
    "date": "1995-07-31",
    "venue": "Garden State Arts Center",
    "city": "Holmdel, NJ",
    "attendees": [
      "April"
    ],
    "comments": "",
    "links": [
      "https://www.setlist.fm/setlist/steve-miller-band/1995/garden-state-arts-center-holmdel-nj-5bd6f74c.html"
    ],
    "imageUrl": "https://via.placeholder.com/300x200",
    "year": 1995
  },
  {
    "id": "weezer-1995-08-03",
    "artist": "Weezer",
    "openers": [],
    "date": "1995-08-03",
    "venue": "Central Park SummerStage",
    "city": "New York, NY",
    "attendees": [
      "Drew"
    ],
    "comments": "We were running late but got there just in time. I think we caught the end of the opening band.",
    "links": [
      "https://www.setlist.fm/setlist/weezer/1995/central-park-summerstage-new-york-ny-5bd6e7e0.html"
    ],
    "imageUrl": "https://via.placeholder.com/300x200",
    "year": 1995
  },
  {
    "id": "dave-matthews-band-1995-08-26",
    "artist": "Dave Matthews Band",
    "openers": [],
    "date": "1995-08-26",
    "venue": "Garden State Arts Center",
    "city": "Holmdel, NJ",
    "attendees": [
      "April"
    ],
    "comments": "I think this was with April's 4H exchange person from Kansas?",
    "links": [
      "https://www.setlist.fm/setlist/dave-matthews-band/1995/garden-state-arts-center-holmdel-nj-1bd681a8.html"
    ],
    "imageUrl": "https://via.placeholder.com/300x200",
    "year": 1995
  },
  {
    "id": "toadies-1996-04-27",
    "artist": "Toadies",
    "openers": [],
    "date": "1996-04-27",
    "venue": "Stone Pony",
    "city": "Asbury Park, NJ",
    "attendees": [
      "Diana",
      "Dana",
      "Melanie"
    ],
    "comments": "This was actually a great show! Played basically the whole album.",
    "links": [
      "https://www.setlist.fm/setlist/toadies/1996/the-stone-pony-asbury-park-nj-6be8664a.html"
    ],
    "imageUrl": "https://via.placeholder.com/300x200",
    "year": 1996
  },
  {
    "id": "ben-harper-1996-06-05",
    "artist": "Ben Harper",
    "openers": [],
    "date": "1996-06-05",
    "venue": "Blockbuster-Sony Music Entertainment Centre",
    "city": "Camden, NJ",
    "attendees": [
      "Sachin"
    ],
    "comments": "I don't remember much about this. There was some crazy bass solo.",
    "links": [
      "https://www.setlist.fm/setlist/ben-harper-and-the-innocent-criminals/1996/blockbuster-sony-music-entertainment-centre-camden-nj-3bdfb450.html"
    ],
    "imageUrl": "https://via.placeholder.com/300x200",
    "year": 1996
  },
  {
    "id": "smashing-pumpkins-1996-07-05",
    "artist": "Smashing Pumpkins",
    "openers": [
      "Garbage"
    ],
    "date": "1996-07-05",
    "venue": "CoreStates Spectrum",
    "city": "Philadelphia, PA",
    "attendees": [
      "Chris",
      "Pete"
    ],
    "comments": "Not great. 20-minute version of 'Silverfuck' with lots of feedback. Hmmm, I think I found the show. Garbage opening sounds familiar.",
    "links": [
      "https://www.setlist.fm/setlist/the-smashing-pumpkins/1996/corestates-spectrum-philadelphia-pa-7bd6f6a8.html"
    ],
    "imageUrl": "https://via.placeholder.com/300x200",
    "year": 1996
  },
  {
    "id": "soundgarden-1996-07-10",
    "artist": "Soundgarden",
    "openers": [],
    "date": "1996-07-10",
    "venue": "Downing Stadium",
    "city": "New York, NY",
    "attendees": [
      "Pete",
      "Sachin"
    ],
    "comments": "Lollapalooza (Metallica, Ben Folds Five)",
    "links": [
      "https://www.setlist.fm/setlist/soundgarden/1996/downing-stadium-new-york-ny-73d6e601.html"
    ],
    "imageUrl": "https://via.placeholder.com/300x200",
    "year": 1996
  },
  {
    "id": "texas-is-the-reason-1996-08-23",
    "artist": "Texas is the Reason",
    "openers": [],
    "date": "1996-08-23",
    "venue": "Trocadero Theatre",
    "city": "Philadelphia, PA",
    "attendees": [
      "Sachin",
      "Gerard"
    ],
    "comments": "",
    "links": [
      "https://www.setlist.fm/setlist/texas-is-the-reason/1996/trocadero-theatre-philadelphia-pa-33c320e1.html"
    ],
    "imageUrl": "https://via.placeholder.com/300x200",
    "year": 1996
  },
  {
    "id": "pearl-jam-1996-09-28",
    "artist": "Pearl Jam",
    "openers": [
      "Ben Harper"
    ],
    "date": "1996-09-28",
    "venue": "Downing Stadium",
    "city": "New York, NY",
    "attendees": [
      "Sachin"
    ],
    "comments": "Sachin won tickets by calling into a radio show, but he also got tickets from being in the fan club. I went with Sach one night and then Chris and Pete went the second night. The show was great, but got a bit scary with how the crowd was moving.",
    "links": [
      "https://www.setlist.fm/setlist/pearl-jam/1996/downing-stadium-new-york-ny-4bd667c2.html",
      "https://www.youtube.com/watch?v=NrQllakeAmQ"
    ],
    "imageUrl": "https://via.placeholder.com/300x200",
    "year": 1996
  },
  {
    "id": "jeremy-enigk-1996-10-13",
    "artist": "Jeremy Enigk",
    "openers": [],
    "date": "1996-10-13",
    "venue": "The Knitting Factory",
    "city": "New York, NY",
    "attendees": [
      "Pete",
      "Chris",
      "Gerard"
    ],
    "comments": "Basically a religious experience.",
    "links": [
      "https://www.setlist.fm/setlist/jeremy-enigk/1996/the-knitting-factory-new-york-ny-6bec7e0e.html"
    ],
    "imageUrl": "https://via.placeholder.com/300x200",
    "year": 1996
  },
  {
    "id": "jeremy-enigk-1996-10-18",
    "artist": "Jeremy Enigk",
    "openers": [],
    "date": "1996-10-18",
    "venue": "Trocadero Theatre",
    "city": "Philadelphia, PA",
    "attendees": [
      "April",
      "Pete",
      "Chris",
      "Gerard"
    ],
    "comments": "Still completely amazing even though this may have been the next night.",
    "links": [
      "https://www.setlist.fm/setlist/jeremy-enigk/1996/trocadero-theatre-philadelphia-pa-4ba81312.html"
    ],
    "imageUrl": "https://via.placeholder.com/300x200",
    "year": 1996
  },
  {
    "id": "weezer-1996-12-05",
    "artist": "Weezer",
    "openers": [
      "Fiona Apple"
    ],
    "date": "1996-12-05",
    "venue": "Electric Factory",
    "city": "Philadelphia, PA",
    "attendees": [
      "Chris"
    ],
    "comments": "",
    "links": [
      "https://www.setlist.fm/setlist/weezer/1996/electric-factory-philadelphia-pa-6bd5f2c2.html",
      "Weezer - (Electric Factory) Philadelphia, Pa 12.5.96 (Complete Show)"
    ],
    "imageUrl": "https://via.placeholder.com/300x200",
    "year": 1996
  },
  {
    "id": "weezer-1997-01-10",
    "artist": "Weezer",
    "openers": [],
    "date": "1997-01-10",
    "venue": "Convention Hall",
    "city": "Asbury Park, NJ",
    "attendees": [
      "April"
    ],
    "comments": "I think April was not happy with this show because it was a bit too loud and she didn't think they sounded good. I thought it was good, but maybe not great.",
    "links": [
      "Weezer Concert Setlist at Convention Hall, Asbury Park on January 10, 1997"
    ],
    "imageUrl": "https://via.placeholder.com/300x200",
    "year": 1997
  },
  {
    "id": "jeremy-enigk-1997-03-09",
    "artist": "Jeremy Enigk",
    "openers": [
      "Hunk Papa"
    ],
    "date": "1997-03-09",
    "venue": "The Middle East",
    "city": "Philadelphia, PA",
    "attendees": [
      "April",
      "Chris",
      "Sachin",
      "Pete",
      "Gerard"
    ],
    "comments": "This show of course had Hunk Papa. Best opening band ever who started and ended with the same song. Also it was way too loud.",
    "links": [
      "https://www.setlist.fm/setlist/jeremy-enigk/1997/the-middle-east-philadelphia-pa-33927461.html"
    ],
    "imageUrl": "https://via.placeholder.com/300x200",
    "year": 1997
  },
  {
    "id": "jeremy-enigk-1997-03-11",
    "artist": "Jeremy Enigk",
    "openers": [],
    "date": "1997-03-11",
    "venue": "The Knitting Factory",
    "city": "New York, NY",
    "attendees": [
      "April",
      "Chris",
      "Sachin",
      "Pete",
      "Gerard"
    ],
    "comments": "This was the end of the second tour when he came back and his hair was short now. I am pretty certain this is the video, because it ends with Chewing Gum:",
    "links": [
      "https://www.setlist.fm/setlist/jeremy-enigk/1997/the-knitting-factory-new-york-ny-73ec7e0d.html",
      "https://www.youtube.com/watch?v=SfPal1lvyEI"
    ],
    "imageUrl": "https://via.placeholder.com/300x200",
    "year": 1997
  },
  {
    "id": "matthew-sweet-1997-06-03",
    "artist": "Matthew Sweet",
    "openers": [],
    "date": "1997-06-03",
    "venue": "Birch Hill Nite Club",
    "city": "Old Bridge, NJ",
    "attendees": [
      "Jeff",
      "Rick"
    ],
    "comments": "This was a really loud show, and it was late and I was tired, that's all I remember.",
    "links": [
      "Matthew Sweet Concert Setlist at Birch Hill Nite Club, Old Bridge on June 3, 1997"
    ],
    "imageUrl": "https://via.placeholder.com/300x200",
    "year": 1997
  },
  {
    "id": "radiohead-1997-06-07",
    "artist": "Radiohead",
    "openers": [
      "John Spencer Blues Explosion",
      "Foo Fighters",
      "Beastie Boys",
      "Blur"
    ],
    "date": "1997-06-07",
    "venue": "Downing Stadium",
    "city": "New York, NY",
    "attendees": [
      "Sachin",
      "Gerard",
      "Chris",
      "Pete"
    ],
    "comments": "Tibetan Freedom Concert",
    "links": [
      "Radiohead Concert Setlist at Tibetan Freedom Concert 1997 on June 7, 1997"
    ],
    "imageUrl": "https://via.placeholder.com/300x200",
    "year": 1997
  },
  {
    "id": "radiohead-1997-06-09",
    "artist": "Radiohead",
    "openers": [],
    "date": "1997-06-09",
    "venue": "Irving Plaza",
    "city": "New York, NY",
    "attendees": [
      "April",
      "Sachin",
      "Pete",
      "Chris",
      "Gerard"
    ],
    "comments": "Right before OK Computer came out but Dimitri got the Japanese version ahead of time so we all knew the songs. Tons of famous people in the audience. Amazing show!",
    "links": [
      "Radiohead Concert Setlist at Irving Plaza, New York on June 9, 1997"
    ],
    "imageUrl": "https://via.placeholder.com/300x200",
    "year": 1997
  },
  {
    "id": "radiohead-1997-08-26",
    "artist": "Radiohead",
    "openers": [],
    "date": "1997-08-26",
    "venue": "Hammerstein Ballroom",
    "city": "New York, NY",
    "attendees": [
      "April",
      "Chris",
      "Sachin",
      "Pete",
      "Gerard"
    ],
    "comments": "",
    "links": [
      "Radiohead Concert Setlist at Hammerstein Ballroom, New York on August 26, 1997"
    ],
    "imageUrl": "https://via.placeholder.com/300x200",
    "year": 1997
  },
  {
    "id": "sunny-day-real-estate-1998-07-17",
    "artist": "Sunny Day Real Estate",
    "openers": [
      "MK Ultra",
      "Shudder to Think"
    ],
    "date": "1998-07-17",
    "venue": "Irving Plaza",
    "city": "New York, NY",
    "attendees": [
      "Gerard",
      "Sachin",
      "Chris"
    ],
    "comments": "That crazy long late show, first time seeing them",
    "links": [
      "https://www.setlist.fm/setlist/sunny-day-real-estate/1998/irving-plaza-new-york-ny-7bd6b5c4.html"
    ],
    "imageUrl": "https://via.placeholder.com/300x200",
    "year": 1998
  },
  {
    "id": "sunny-day-real-estate-1998-09-27",
    "artist": "Sunny Day Real Estate",
    "openers": [],
    "date": "1998-09-27",
    "venue": "Trocadero Theatre",
    "city": "Philadelphia, PA",
    "attendees": [],
    "comments": "This is a guess. I know we saw them again, maybe in NY again?",
    "links": [
      "https://www.setlist.fm/setlist/sunny-day-real-estate/1998/trocadero-theatre-philadelphia-pa-43e11ffb.html"
    ],
    "imageUrl": "https://via.placeholder.com/300x200",
    "year": 1998
  },
  {
    "id": "elliott-smith-2000-05-17",
    "artist": "Elliott Smith",
    "openers": [],
    "date": "2000-05-17",
    "venue": "Irving Plaza",
    "city": "New York, NY",
    "attendees": [],
    "comments": "No idea when this was, after Figure Eight? This is a total guess. No idea who went with me either.",
    "links": [
      "https://www.setlist.fm/setlist/elliott-smith/2000/irving-plaza-new-york-ny-53de17f5.html"
    ],
    "imageUrl": "https://via.placeholder.com/300x200",
    "year": 2000
  },
  {
    "id": "sunny-day-real-estate-2000-10-16",
    "artist": "Sunny Day Real Estate",
    "openers": [],
    "date": "2000-10-16",
    "venue": "Birch Hill Nite Club",
    "city": "Old Bridge, NJ",
    "attendees": [
      "Sachin",
      "Gerard"
    ],
    "comments": "",
    "links": [
      "https://www.setlist.fm/setlist/sunny-day-real-estate/2000/birch-hill-nite-club-old-bridge-nj-3bd74474.html"
    ],
    "imageUrl": "https://via.placeholder.com/300x200",
    "year": 2000
  },
  {
    "id": "aimee-mann-2001-01-22",
    "artist": "Aimee Mann",
    "openers": [
      "Michael Penn"
    ],
    "date": "2001-01-22",
    "venue": "The Town Hall",
    "city": "New York, NY",
    "attendees": [
      "Jeff"
    ],
    "comments": "I guess after Bachelor No.2. Patton Oswalt opened doing standup. They asked for a juggler from the crowd and the guy they found did the eat the apple while juggling trick. Should've been me.",
    "links": [
      "https://www.setlist.fm/setlist/aimee-mann-and-michael-penn/2001/the-town-hall-new-york-ny-13eef11d.html"
    ],
    "imageUrl": "https://via.placeholder.com/300x200",
    "year": 2001
  },
  {
    "id": "16-horsepower-2001-03-03",
    "artist": "16 Horsepower",
    "openers": [
      "Slim Cessna's Auto Club"
    ],
    "date": "2001-03-03",
    "venue": "Bowery Ballroom",
    "city": "New York, NY",
    "attendees": [
      "Chris",
      "Sachin"
    ],
    "comments": "Black Lung was so good",
    "links": [
      "https://www.setlist.fm/setlist/16-horsepower/2001/bowery-ballroom-new-york-ny-7bcc12f4.html"
    ],
    "imageUrl": "https://via.placeholder.com/300x200",
    "year": 2001
  },
  {
    "id": "sarah-brightman-2001-03-24",
    "artist": "Sarah Brightman",
    "openers": [],
    "date": "2001-03-24",
    "venue": "Radio City Music Hall",
    "city": "New York, NY",
    "attendees": [
      "April"
    ],
    "comments": "",
    "links": [
      "https://www.setlist.fm/setlist/sarah-brightman/2001/radio-city-music-hall-new-york-ny-7bc9e2fc.html"
    ],
    "imageUrl": "https://via.placeholder.com/300x200",
    "year": 2001
  },
  {
    "id": "coldplay-2001-06-02",
    "artist": "Coldplay",
    "openers": [],
    "date": "2001-06-02",
    "venue": "Electric Factory",
    "city": "Philadelphia, PA",
    "attendees": [
      "Sachin"
    ],
    "comments": "I don't remember much about this. There was some crazy bass solo",
    "links": [
      "https://www.setlist.fm/setlist/coldplay/2001/electric-factory-philadelphia-pa-6bd65eea.html"
    ],
    "imageUrl": "https://via.placeholder.com/300x200",
    "year": 2001
  },
  {
    "id": "radiohead-2003-08-18",
    "artist": "Radiohead",
    "openers": [],
    "date": "2003-08-18",
    "venue": "Tweeter Center",
    "city": "Camden, NJ",
    "attendees": [
      "Sachin",
      "Anthony"
    ],
    "comments": "April was supposed to originally go but changed her mind so Anthony was able to go last minute. I think Gerard and Chris were there but they were in the back? Sachin got special tickets through the website perhaps? We were pretty close to the stage.",
    "links": [
      "https://www.setlist.fm/setlist/radiohead/2003/tweeter-center-at-the-waterfront-camden-nj-3d681d7.html"
    ],
    "imageUrl": "https://via.placeholder.com/300x200",
    "year": 2003
  },
  {
    "id": "the-mars-volta-2003-10-21",
    "artist": "The Mars Volta",
    "openers": [],
    "date": "2003-10-21",
    "venue": "Electric Factory",
    "city": "Philadelphia, PA",
    "attendees": [],
    "comments": "",
    "links": [
      "https://www.setlist.fm/setlist/the-mars-volta/2003/electric-factory-philadelphia-pa-43f62b6b.html"
    ],
    "imageUrl": "https://via.placeholder.com/300x200",
    "year": 2003
  },
  {
    "id": "sufjan-stevens-2005-01-01",
    "artist": "Sufjan Stevens",
    "openers": [
      "Damien Rice",
      "Antony and the Johnsons"
    ],
    "date": "2005-01-01",
    "venue": "Carnegie Hall",
    "city": "New York, NY",
    "attendees": [],
    "comments": "This was a weird show where everyone played only a couple songs. Sufjan and Damien Rice sounded amazing, but wish they played longer.",
    "links": [],
    "imageUrl": "https://via.placeholder.com/300x200",
    "year": 2005
  },
  {
    "id": "arcade-fire-2005-01-01",
    "artist": "Arcade Fire",
    "openers": [
      "The National"
    ],
    "date": "2005-01-01",
    "venue": "",
    "city": "New York, NY",
    "attendees": [],
    "comments": "Don't remember this at all, but I know I saw them more than once.",
    "links": [],
    "imageUrl": "https://via.placeholder.com/300x200",
    "year": 2005
  },
  {
    "id": "ambulance-ltd-2005-03-07",
    "artist": "Ambulance LTD",
    "openers": [],
    "date": "2005-03-07",
    "venue": "Bowery Ballroom",
    "city": "New York, NY",
    "attendees": [],
    "comments": "Ran into Jeff and Rick and had dinner with them after the show. This was with the lead singer and his replacement band (all the original guys had left). Regardless, it was awesome to hear that album played live.",
    "links": [],
    "imageUrl": "https://via.placeholder.com/300x200",
    "year": 2005
  },
  {
    "id": "death-cab-for-cutie-2005-08-18",
    "artist": "Death Cab For Cutie",
    "openers": [
      "The Decemberists"
    ],
    "date": "2005-08-18",
    "venue": "Central Park SummerStage",
    "city": "New York, NY",
    "attendees": [],
    "comments": "I didn't realize this was one show with both Decemberists and Death Cab!",
    "links": [],
    "imageUrl": "https://via.placeholder.com/300x200",
    "year": 2005
  },
  {
    "id": "arcade-fire-2005-09-16",
    "artist": "Arcade Fire",
    "openers": [],
    "date": "2005-09-16",
    "venue": "Central Park SummerStage",
    "city": "New York, NY",
    "attendees": [],
    "comments": "This was one of the best shows in a long while. They were amazing and then David Bowie walked on stage!",
    "links": [],
    "imageUrl": "https://via.placeholder.com/300x200",
    "year": 2005
  },
  {
    "id": "sufjan-stevens-2006-09-28",
    "artist": "Sufjan Stevens",
    "openers": [],
    "date": "2006-09-28",
    "venue": "Tower Theatre",
    "city": "Philadelphia, PA",
    "attendees": [],
    "comments": "Drove through bad area of Philly to get there; this was our first time seeing him.",
    "links": [],
    "imageUrl": "https://via.placeholder.com/300x200",
    "year": 2006
  },
  {
    "id": "built-to-spill-2006-01-01",
    "artist": "Built to Spill",
    "openers": [],
    "date": "2006-01-01",
    "venue": "New York",
    "city": "New York, NY",
    "attendees": [],
    "comments": "You In Reverse tour. I remember it started with some weird drawings.",
    "links": [],
    "imageUrl": "https://via.placeholder.com/300x200",
    "year": 2006
  },
  {
    "id": "bloc-party-2006-01-01",
    "artist": "Bloc Party",
    "openers": [],
    "date": "2006-01-01",
    "venue": "New York",
    "city": "New York, NY",
    "attendees": [],
    "comments": "This was a fun show! Drummer had so much energy!",
    "links": [],
    "imageUrl": "https://via.placeholder.com/300x200",
    "year": 2006
  },
  {
    "id": "snowden-2006-01-01",
    "artist": "Snowden",
    "openers": [],
    "date": "2006-01-01",
    "venue": "North Star Bar",
    "city": "Philadelphia, PA",
    "attendees": [],
    "comments": "They were actually opening and I don't even remember the headliners, but there was barely anyone there and we went outside after the show and they were there and we briefly talked. They were great!",
    "links": [],
    "imageUrl": "https://via.placeholder.com/300x200",
    "year": 2006
  },
  {
    "id": "jeremy-enigk-2006-08-11",
    "artist": "Jeremy Enigk",
    "openers": [],
    "date": "2006-08-11",
    "venue": "Bowery Ballroom",
    "city": "New York, NY",
    "attendees": [],
    "comments": "",
    "links": [
      "https://www.setlist.fm/setlist/jeremy-enigk/2006/bowery-ballroom-new-york-ny-bce9196.html"
    ],
    "imageUrl": "https://via.placeholder.com/300x200",
    "year": 2006
  },
  {
    "id": "jeremy-enigk-2006-08-12",
    "artist": "Jeremy Enigk",
    "openers": [],
    "date": "2006-08-12",
    "venue": "North Star Bar",
    "city": "Philadelphia, PA",
    "attendees": [],
    "comments": "",
    "links": [
      "https://www.setlist.fm/setlist/jeremy-enigk/2006/north-star-bar-philadelphia-pa-23875c3b.html"
    ],
    "imageUrl": "https://via.placeholder.com/300x200",
    "year": 2006
  },
  {
    "id": "the-national-2007-01-01",
    "artist": "The National",
    "openers": [],
    "date": "2007-01-01",
    "venue": "Central Park",
    "city": "New York, NY",
    "attendees": [],
    "comments": "This was alright, but the singing sounded flat.",
    "links": [],
    "imageUrl": "https://via.placeholder.com/300x200",
    "year": 2007
  },
  {
    "id": "clap-your-hands-say-yeah-2007-01-01",
    "artist": "Clap Your Hands Say Yeah",
    "openers": [
      "Kimya Dawson"
    ],
    "date": "2007-01-01",
    "venue": "Philadelphia",
    "city": "Philadelphia, PA",
    "attendees": [],
    "comments": "My car got stuck in this garage after the show.",
    "links": [],
    "imageUrl": "https://via.placeholder.com/300x200",
    "year": 2007
  },
  {
    "id": "jeremy-enigk-2007-10-09",
    "artist": "Jeremy Enigk",
    "openers": [
      "Kevin Devine"
    ],
    "date": "2007-10-09",
    "venue": "Highline Ballroom",
    "city": "New York, NY",
    "attendees": [],
    "comments": "",
    "links": [
      "https://www.nytimes.com/2007/10/05/arts/music/05wpop.html"
    ],
    "imageUrl": "https://via.placeholder.com/300x200",
    "year": 2007
  },
  {
    "id": "built-to-spill-2008-01-01",
    "artist": "Built to Spill",
    "openers": [],
    "date": "2008-01-01",
    "venue": "New York",
    "city": "New York, NY",
    "attendees": [],
    "comments": "Perfect from Now On, and then first few songs of Keep It Like a Secret?",
    "links": [],
    "imageUrl": "https://via.placeholder.com/300x200",
    "year": 2008
  },
  {
    "id": "the-decemberists-2008-01-01",
    "artist": "The Decemberists",
    "openers": [],
    "date": "2008-01-01",
    "venue": "New York",
    "city": "New York, NY",
    "attendees": [],
    "comments": "I think Obama must have just won and there was an Obama cutout crowd surfing at the end of the show.",
    "links": [],
    "imageUrl": "https://via.placeholder.com/300x200",
    "year": 2008
  },
  {
    "id": "joanna-newsom-2008-02-01",
    "artist": "Joanna Newsom",
    "openers": [],
    "date": "2008-02-01",
    "venue": "Brooklyn Academy of Music (BAM)",
    "city": "Brooklyn, NY",
    "attendees": [],
    "comments": "This was an incredible show.",
    "links": [],
    "imageUrl": "https://via.placeholder.com/300x200",
    "year": 2008
  },
  {
    "id": "wolf-parade-2008-07-31",
    "artist": "Wolf Parade",
    "openers": [],
    "date": "2008-07-31",
    "venue": "Terminal 5",
    "city": "New York, NY",
    "attendees": [],
    "comments": "",
    "links": [
      "https://www.setlist.fm/setlist/wolf-parade/2008/terminal-5-new-york-ny-3e74de3.html"
    ],
    "imageUrl": "https://via.placeholder.com/300x200",
    "year": 2008
  },
  {
    "id": "sunny-day-real-estate-2009-10-01",
    "artist": "Sunny Day Real Estate",
    "openers": [],
    "date": "2009-10-01",
    "venue": "Trocadero Theatre",
    "city": "Philadelphia, PA",
    "attendees": [],
    "comments": "",
    "links": [
      "https://www.setlist.fm/setlist/sunny-day-real-estate/2009/trocadero-theatre-philadelphia-pa-53f65bcd.html"
    ],
    "imageUrl": "https://via.placeholder.com/300x200",
    "year": 2009
  },
  {
    "id": "joanna-newsom-2010-11-23",
    "artist": "Joanna Newsom",
    "openers": [],
    "date": "2010-11-23",
    "venue": "Carnegie Hall",
    "city": "New York, NY",
    "attendees": [],
    "comments": "",
    "links": [
      "https://www.setlist.fm/setlist/joanna-newsom/2010/carnegie-hall-new-york-ny-33d2b88d.html"
    ],
    "imageUrl": "https://via.placeholder.com/300x200",
    "year": 2010
  },
  {
    "id": "owl-city-2011-06-25",
    "artist": "Owl City",
    "openers": [],
    "date": "2011-06-25",
    "venue": "Mann Center",
    "city": "Philadelphia, PA",
    "attendees": [],
    "comments": "",
    "links": [],
    "imageUrl": "https://via.placeholder.com/300x200",
    "year": 2011
  },
  {
    "id": "jeff-mangum-2012-01-20",
    "artist": "Jeff Mangum",
    "openers": [],
    "date": "2012-01-20",
    "venue": "Brooklyn Academy of Music (BAM)",
    "city": "Brooklyn, NY",
    "attendees": [],
    "comments": "",
    "links": [],
    "imageUrl": "images/jeff-mangum.jpg",
    "year": 2012
  },
  {
    "id": "pj-harvey-2017-04-22",
    "artist": "PJ Harvey",
    "openers": [
      "The National"
    ],
    "date": "2017-04-22",
    "venue": "Richmond Coliseum",
    "city": "Richmond, VA",
    "attendees": [],
    "comments": "",
    "links": [],
    "imageUrl": "images/pj-harvey-17.jpg",
    "year": 2017
  },
  {
    "id": "jeremy-enigk-2018-06-23",
    "artist": "Jeremy Enigk",
    "openers": [],
    "date": "2018-06-23",
    "venue": "Union Transfer",
    "city": "Philadelphia, PA",
    "attendees": [],
    "comments": "Return of the Frog Queen full album performance",
    "links": [
      "https://www.setlist.fm/setlist/jeremy-enigk/2018/union-transfer-philadelphia-pa-3bea3c6c.html"
    ],
    "imageUrl": "images/jeremy-enigk-18.jpg",
    "year": 2018
  },
  {
    "id": "sleater-kinney-2019-10-25",
    "artist": "Sleater-Kinney",
    "openers": [],
    "date": "2019-10-25",
    "venue": "The Anthem",
    "city": "Washington, DC",
    "attendees": [],
    "comments": "This was an awesome show and just a great night in general. Got to see part of The Nationals in the playoff, and the concert was way better than I thought. Not that I wasn't expecting it to be good, but they played a great set.",
    "links": [
      "https://www.setlist.fm/setlist/sleaterkinney/2019/the-anthem-washington-dc-5b9dd7cc.html"
    ],
    "imageUrl": "images/sleater-kinney-19.jpg",
    "year": 2019
  },
  {
    "id": "big-thief-2022-04-21",
    "artist": "Big Thief",
    "openers": [],
    "date": "2022-04-21",
    "venue": "The Anthem",
    "city": "Washington, DC",
    "attendees": [],
    "comments": "",
    "links": [
      "https://www.setlist.fm/setlist/big-thief/2022/the-anthem-washington-dc-bb6096e.html"
    ],
    "imageUrl": "images/big-thief.jpg",
    "year": 2022
  },
  {
    "id": "sunny-day-real-estate-2022-10-01",
    "artist": "Sunny Day Real Estate",
    "openers": [],
    "date": "2022-10-01",
    "venue": "The Fillmore",
    "city": "Philadelphia, PA",
    "attendees": [],
    "comments": "",
    "links": [
      "https://photos.google.com/search/_cAF1QipMDleXuxHT4~uZNPUa6XqiCw-Fl1gadtGO0_Peter%20Ruggeri/photo/AF1QipOwCYkxJdKmus9zwr1rF9R5NZEgN9zWLnaggUIp"
    ],
    "imageUrl": "images/sunny-day-filmore.jpg",
    "year": 2022
  },
  {
    "id": "lyn-lapid-2023-06-11",
    "artist": "Lyn Lapid",
    "openers": [
      "Stephanie Poetri"
    ],
    "date": "2023-06-11",
    "venue": "Union Stage",
    "city": "Washington, DC",
    "attendees": [],
    "comments": "",
    "links": [
      "https://www.concertarchives.org/concerts/lyn-lapid-stephanie-poetri-at-union-stage"
    ],
    "imageUrl": "images/lyn-lapid.jpg",
    "year": 2023
  },
  {
    "id": "death-cab-for-cutie-2023-09-14",
    "artist": "Death Cab For Cutie",
    "openers": [
      "The Postal Service"
    ],
    "date": "2023-09-14",
    "venue": "Merriweather Post Pavilion",
    "city": "Columbia, MD",
    "attendees": [],
    "comments": "",
    "links": [
      "https://www.setlist.fm/setlist/death-cab-for-cutie/2023/merriweather-post-pavilion-columbia-md-3ba224d0.html"
    ],
    "imageUrl": "images/death-cab-24.jpg",
    "year": 2023
  },
  {
    "id": "mitski-2024-09-01",
    "artist": "Mitski",
    "openers": [],
    "date": "2024-09-01",
    "venue": "Merriweather Post Pavilion",
    "city": "Columbia, MD",
    "attendees": [],
    "comments": "It was so awesome to see Mitski with Lucy, Sadie, and Cal! It made the show even better. We met up right before Mitski got on with Andy and Jenn as well but they were sitting in a different section.",
    "links": [
      "https://www.setlist.fm/setlist/mitski/2024/merriweather-post-pavilion-columbia-md-7b562ec4.html"
    ],
    "imageUrl": "images/mitski.jpg",
    "year": 2024
  },
  {
    "id": "pj-harvey-2024-09-11",
    "artist": "PJ Harvey",
    "openers": [],
    "date": "2024-09-11",
    "venue": "The Anthem",
    "city": "Washington, DC",
    "attendees": [],
    "comments": "",
    "links": [
      "https://www.setlist.fm/setlist/pj-harvey/2024/the-anthem-washington-dc-43576bf7.html"
    ],
    "imageUrl": "images/pj-harvey-24.jpg",
    "year": 2024
  }
]